README.rst
setup.cfg
setup.py
./__init__.py
./carrier.py
./channel.py
./channel.xml
./party.py
./party.xml
./product.py
./product.xml
./sale.py
./sale.xml
./tryton.cfg
./user.py
./user.xml
./wizard.py
./wizard.xml
./locale/de_DE.po
./tests/__init__.py
./tests/test_sale_channel.py
./view/channel_carrier_form.xml
./view/channel_carrier_tree.xml
./view/channel_exception_form.xml
./view/channel_exception_tree.xml
./view/channel_payment_gateway_form.xml
./view/channel_payment_gateway_tree.xml
./view/listing_add_start_form.xml
./view/order_states_form.xml
./view/order_states_tree.xml
./view/party_channel_listing_tree.xml
./view/party_form.xml
./view/product_channel_listing_form.xml
./view/product_channel_listing_tree.xml
./view/product_form.xml
./view/sale_channel_form.xml
./view/sale_channel_tree.xml
./view/sale_form.xml
./view/sale_tax_form.xml
./view/sale_tax_tree.xml
./view/sale_tree.xml
./view/template_channel_listing_tree.xml
./view/template_form.xml
./view/user_form.xml
./view/user_form_preferences.xml
./view/wizard_export_data_start_form.xml
./view/wizard_export_data_success_form.xml
./view/wizard_export_prices_start_form.xml
./view/wizard_export_prices_status_form.xml
./view/wizard_import_data_properties_form.xml
./view/wizard_import_data_start_form.xml
./view/wizard_import_data_success_form.xml
./view/wizard_import_order_states_start_form.xml
fio_sale_channel.egg-info/PKG-INFO
fio_sale_channel.egg-info/SOURCES.txt
fio_sale_channel.egg-info/dependency_links.txt
fio_sale_channel.egg-info/entry_points.txt
fio_sale_channel.egg-info/not-zip-safe
fio_sale_channel.egg-info/requires.txt
fio_sale_channel.egg-info/top_level.txt